flask_principal-stubs/__init__.pyi
flask_principal-stubs/flask_principal.pyi
flask_principal-stubs/idx.txt
flask_principal-stubs/metadata.json
flask_principal-stubs/py.typed
flask_resources-stubs/__init__.pyi
flask_resources-stubs/config.pyi
flask_resources-stubs/content_negotiation.pyi
flask_resources-stubs/context.pyi
flask_resources-stubs/errors.pyi
flask_resources-stubs/idx.txt
flask_resources-stubs/resources.pyi
flask_resources-stubs/responses.pyi
flask_resources-stubs/deserializers/__init__.pyi
flask_resources-stubs/deserializers/base.pyi
flask_resources-stubs/deserializers/json.pyi
flask_resources-stubs/parsers/__init__.pyi
flask_resources-stubs/parsers/base.pyi
flask_resources-stubs/parsers/body.pyi
flask_resources-stubs/parsers/decorators.pyi
flask_resources-stubs/parsers/schema.pyi
flask_resources-stubs/serializers/__init__.pyi
flask_resources-stubs/serializers/base.pyi
flask_resources-stubs/serializers/csv.pyi
flask_resources-stubs/serializers/json.pyi
flask_resources-stubs/serializers/simple.pyi
invenio_audit_logs-stubs/__init__.pyi
invenio_audit_logs-stubs/config.pyi
invenio_audit_logs-stubs/ext.pyi
invenio_audit_logs-stubs/metadata.json
invenio_audit_logs-stubs/proxies.pyi
invenio_audit_logs-stubs/views.pyi
invenio_audit_logs-stubs/alembic/1743073617_create_audit_logs_branch.pyi
invenio_audit_logs-stubs/alembic/1743073720_create_audit_logs_table.pyi
invenio_audit_logs-stubs/records/__init__.pyi
invenio_audit_logs-stubs/records/api.pyi
invenio_audit_logs-stubs/records/models.pyi
invenio_audit_logs-stubs/records/systemfields/__init__.pyi
invenio_audit_logs-stubs/records/systemfields/action.pyi
invenio_audit_logs-stubs/resources/__init__.pyi
invenio_audit_logs-stubs/resources/config.pyi
invenio_audit_logs-stubs/resources/resource.pyi
invenio_audit_logs-stubs/services/__init__.pyi
invenio_audit_logs-stubs/services/action.pyi
invenio_audit_logs-stubs/services/config.pyi
invenio_audit_logs-stubs/services/permissions.pyi
oarepo_invenio_typing_stubs-0.1.28.dist-info/METADATA
oarepo_invenio_typing_stubs-0.1.28.dist-info/WHEEL
oarepo_invenio_typing_stubs-0.1.28.dist-info/RECORD
