Metadata-Version: 2.4
Name: oarepo-invenio-typing-stubs
Version: 0.1.28
Summary: OAREPO typing package for invenio packages. Stub files only.
Requires-Python: >=3.13
Requires-Dist: celery-types
Provides-Extra: tests
Requires-Dist: mypy; extra == 'tests'
Requires-Dist: pyright; extra == 'tests'
Requires-Dist: pytest>=8.4.2; extra == 'tests'
Requires-Dist: types-lxml>=2025.8.25; extra == 'tests'
